project_mcp_tools/__init__.py
project_mcp_tools/server.py
project_mcp_tools/tools/__init__.py
project_mcp_tools/tools/edit_file.py
project_mcp_tools/tools/grep.py
project_mcp_tools/tools/list_files.py
project_mcp_tools/tools/multi_edit_file.py
project_mcp_tools/tools/read_file.py
project_mcp_tools/tools/search_glob.py
project_mcp_tools/tools/session_manager.py
project_mcp_tools/tools/write_file.py
project_mcp_tools-0.1.2.dist-info/METADATA
project_mcp_tools-0.1.2.dist-info/WHEEL
project_mcp_tools-0.1.2.dist-info/entry_points.txt
project_mcp_tools-0.1.2.dist-info/RECORD
