Metadata-Version: 2.4
Name: project-mcp-tools
Version: 0.1.2
Summary: Collection of FastMCP tools for software project management and development
Requires-Python: >=3.11
Requires-Dist: fastmcp>=2.11.0
Provides-Extra: dev
Requires-Dist: pytest-asyncio>=0.21.0; extra == 'dev'
Requires-Dist: pytest>=7.0.0; extra == 'dev'
